upscale/__init__.py
upscale/masking/importance.py
upscale/masking/mask.py
upscale/masking/utils.py
upscale/pruning/__init__.py
upscale/pruning/manager.py
upscale/pruning/mock.py
upscale/pruning/pruner.py
upscale/pruning/reorder.py
upscale/pruning/resolve.py
upscale/pruning/trace.py
upscale/pruning/tracing.py
upscale/pruning/utils.py
apple_upscale-0.1.1.dist-info/LICENSE
apple_upscale-0.1.1.dist-info/METADATA
apple_upscale-0.1.1.dist-info/WHEEL
apple_upscale-0.1.1.dist-info/top_level.txt
apple_upscale-0.1.1.dist-info/RECORD
