Metadata-Version: 2.1
Name: apple-upscale
Version: 0.1.1
Summary: Export utility for unconstrained channel pruned models
Author-email: Alvin Wan <alvinwan@apple.com>
License: Copyright (C) 2023 Apple Inc. All Rights Reserved.
Project-URL: Homepage, https://github.com/apple/ml-upscale
Project-URL: Bug Reports, https://github.com/apple/ml-upscale/issues
Project-URL: Source, https://github.com/apple/ml-upscale
Keywords: pruning,export,unconstrained pruning
Classifier: Development Status :: 3 - Alpha
Classifier: Intended Audience :: Developers
Classifier: Topic :: Software Development :: Build Tools
Classifier: License :: OSI Approved :: Apple Public Source License
Classifier: Programming Language :: Python :: 3
Classifier: Programming Language :: Python :: 3.7
Classifier: Programming Language :: Python :: 3.8
Classifier: Programming Language :: Python :: 3.9
Classifier: Programming Language :: Python :: 3.10
Classifier: Programming Language :: Python :: 3.11
Classifier: Programming Language :: Python :: 3 :: Only
Requires-Python: >=3.7
License-File: LICENSE
Requires-Dist: seaborn (==0.12.1)
Requires-Dist: torch (==2.0.1)
Requires-Dist: torchvision (==0.15.2)
Requires-Dist: yacs (==0.1.8)
Requires-Dist: ninja (==1.10.2.3)
Provides-Extra: test
Requires-Dist: pytest (==7.3.2) ; extra == 'test'
